{"footonsat": [{"compet": "Spanish La Liga (Primera) - Week 24", "match": "     Girona   vs   Getafe", "flags": {"team1": "spain", "team2": "spain"}, "time": "20:00", "date": "2025-02-14"}, {"channel": "beIN Sports MENA 3 HD", "sat": "Eshail 2 25.5\u00b0e", "freq": "10810 H 27500 - 2/3", "encry": "HD Irdeto", "link": "#", "related_to": "     Girona   vs   Getafe"}, {"channel": "Eleven Sports 3 Polska HD", "sat": "Hotbird 13F 13.0\u00b0e", "freq": "11488 H 27500 - 3/4", "encry": "HD Conax", "link": "#", "related_to": "     Girona   vs   Getafe"}, {"channel": "LaLiga TV Bar Espa\u00f1a HD", "sat": "Astra 1M 19.2\u00b0e", "freq": "10876 V 22000 - 5/6", "encry": "NagraVision", "link": "#", "related_to": "     Girona   vs   Getafe"}, {"channel": "MAX Sport 4 Bulgaria HD", "sat": "AzerSpace 2 45.0\u00b0e", "freq": "11475 V 30000 - 5/6", "encry": "HD VideoGuard", "link": "#", "related_to": "     Girona   vs   Getafe"}, {"channel": "ONE Sport Israel HD", "sat": "Amos 3 4.0\u00b0w", "freq": "10806 V 27500 - 3/4", "encry": "VideoGuard", "link": "#", "related_to": "     Girona   vs   Getafe"}, {"channel": "Premier Sports GB Player HD", "sat": "* IPTV/Stream 0.0\u00b0", "freq": "0000 0", "encry": "", "link": "https://www.premiersports.com/fr/live-now-on-demand", "related_to": "     Girona   vs   Getafe"}, {"channel": "Ziggo Sport 2", "sat": "Astra 3B 23.5\u00b0e", "freq": "12129 V 29900 - 3/4", "encry": "MPEG-4 Viaccess", "link": "#", "related_to": "     Girona   vs   Getafe"}, {"compet": "Spanish La Liga (Primera) - Week 24", "match": "     Legan\u00e9s   vs   Alav\u00e9s", "flags": {"team1": "spain", "team2": "spain"}, "time": "13:00", "date": "2025-02-15"}, {"channel": "beIN Sports MENA 4 HD", "sat": "Eshail 2 25.5\u00b0e", "freq": "10810 V 27500 - 2/3", "encry": "HD Irdeto", "link": "#", "related_to": "     Legan\u00e9s   vs   Alav\u00e9s"}, {"channel": "ETB 1 Basque Country", "sat": "*DTT 0.0\u00b0-", "freq": "0000 - -", "encry": "MPEG-4 Viaccess", "link": "#", "related_to": "     Legan\u00e9s   vs   Alav\u00e9s"}, {"channel": "GOL Play Espa\u00f1a HD", "sat": "*DTT 0.0\u00b0-", "freq": "0000 - -", "encry": "NagraVision", "link": "https://www.goltelevision.com/en-directo", "related_to": "     Legan\u00e9s   vs   Alav\u00e9s"}, {"channel": "LaLiga TV Bar Espa\u00f1a HD", "sat": "Astra 1M 19.2\u00b0e", "freq": "10876 V 22000 - 5/6", "encry": "NagraVision", "link": "#", "related_to": "     Legan\u00e9s   vs   Alav\u00e9s"}, {"channel": "Premier Sports 1 UK HD", "sat": "Astra 2G 28.2\u00b0e", "freq": "11686 V 23000 - 2/3", "encry": "HD VideoGuard", "link": "#", "related_to": "     Legan\u00e9s   vs   Alav\u00e9s"}, {"channel": "Premier Sports GB Player HD", "sat": "* IPTV/Stream 0.0\u00b0", "freq": "0000 0", "encry": "", "link": "https://www.premiersports.com/fr/live-now-on-demand", "related_to": "     Legan\u00e9s   vs   Alav\u00e9s"}, {"channel": "Telemadrid (Espa\u00f1a)", "sat": "*DTT 0.0\u00b0-", "freq": "0000 - 0", "encry": "FTA", "link": "https://www.telemadrid.es/emision-en-directo/", "related_to": "     Legan\u00e9s   vs   Alav\u00e9s"}, {"channel": "Ziggo Sport HD", "sat": "Astra 3B 23.5\u00b0e", "freq": "12129 V 29900 - 3/4", "encry": "HD Viaccess", "link": "#", "related_to": "     Legan\u00e9s   vs   Alav\u00e9s"}, {"compet": "Spanish La Liga (Primera) - Week 24", "match": "     Osasuna   vs   Real Madrid", "flags": {"team1": "spain", "team2": "spain"}, "time": "15:15", "date": "2025-02-15"}, {"channel": "beIN Sports Australia 2 HD", "sat": "* IPTV/Stream 0.0\u00b0", "freq": "0000 ", "encry": "LiveOnSat.com", "link": "#", "related_to": "     Osasuna   vs   Real Madrid"}, {"channel": "beIN Sports France 2 HD", "sat": "Astra 1M 19.2\u00b0e", "freq": "11856 V 29700 - 2/3", "encry": "HD Viaccess", "link": "#", "related_to": "     Osasuna   vs   Real Madrid"}, {"channel": "beIN Sports MENA 3 HD", "sat": "Eshail 2 25.5\u00b0e", "freq": "10810 H 27500 - 2/3", "encry": "HD Irdeto", "link": "#", "related_to": "     Osasuna   vs   Real Madrid"}, {"channel": "beIN Sports MENA French 1 HD", "sat": "Eshail 2 25.5\u00b0e", "freq": "11390 V 27500 - 2/3", "encry": "HD Irdeto", "link": "#", "related_to": "     Osasuna   vs   Real Madrid"}, {"channel": "LaLiga TV Bar Espa\u00f1a HD", "sat": "Astra 1M 19.2\u00b0e", "freq": "10876 V 22000 - 5/6", "encry": "NagraVision", "link": "#", "related_to": "     Osasuna   vs   Real Madrid"}, {"channel": "Premier Sports GB Player HD", "sat": "* IPTV/Stream 0.0\u00b0", "freq": "0000 0", "encry": "", "link": "https://www.premiersports.com/fr/live-now-on-demand", "related_to": "     Osasuna   vs   Real Madrid"}, {"channel": "Ziggo Sport HD", "sat": "Astra 3B 23.5\u00b0e", "freq": "12129 V 29900 - 3/4", "encry": "HD Viaccess", "link": "#", "related_to": "     Osasuna   vs   Real Madrid"}, {"compet": "Spanish La Liga (Primera) - Week 24", "match": "     Atl\u00e9tico Madrid   vs   Celta Vigo", "flags": {"team1": "spain", "team2": "spain"}, "time": "17:30", "date": "2025-02-15"}, {"channel": "beIN Sports Australia 2 HD", "sat": "* IPTV/Stream 0.0\u00b0", "freq": "0000 ", "encry": "LiveOnSat.com", "link": "#", "related_to": "     Atl\u00e9tico Madrid   vs   Celta Vigo"}, {"channel": "beIN Sports France 4 HD max", "sat": "Astra 1M 19.2\u00b0e", "freq": "11856 V 29700 - 2/3", "encry": "HD NagraVision", "link": "#", "related_to": "     Atl\u00e9tico Madrid   vs   Celta Vigo"}, {"channel": "beIN Sports MENA Xtra 1 HD", "sat": "Eshail 2 25.5\u00b0e", "freq": "10850 H 27500 - 2/3", "encry": "HD Irdeto", "link": "#", "related_to": "     Atl\u00e9tico Madrid   vs   Celta Vigo"}, {"channel": "Canal+ Sport 1 Polska HD", "sat": "Hotbird 13G 13.0\u00b0e", "freq": "11278 V 27500 - 3/4", "encry": "HD Conax", "link": "#", "related_to": "     Atl\u00e9tico Madrid   vs   Celta Vigo"}, {"channel": "LaLiga TV Bar Espa\u00f1a HD", "sat": "Astra 1M 19.2\u00b0e", "freq": "10876 V 22000 - 5/6", "encry": "NagraVision", "link": "#", "related_to": "     Atl\u00e9tico Madrid   vs   Celta Vigo"}, {"channel": "Premier Sports GB Player HD", "sat": "* IPTV/Stream 0.0\u00b0", "freq": "0000 0", "encry": "", "link": "https://www.premiersports.com/fr/live-now-on-demand", "related_to": "     Atl\u00e9tico Madrid   vs   Celta Vigo"}, {"channel": "Ziggo Sport HD", "sat": "Astra 3B 23.5\u00b0e", "freq": "12129 V 29900 - 3/4", "encry": "HD Viaccess", "link": "#", "related_to": "     Atl\u00e9tico Madrid   vs   Celta Vigo"}, {"compet": "Spanish La Liga (Primera) - Week 24", "match": "     Villarreal   vs   Valencia", "flags": {"team1": "spain", "team2": "spain"}, "time": "20:00", "date": "2025-02-15"}, {"channel": "beIN Sports Australia 2 HD", "sat": "* IPTV/Stream 0.0\u00b0", "freq": "0000 ", "encry": "LiveOnSat.com", "link": "#", "related_to": "     Villarreal   vs   Valencia"}, {"channel": "beIN Sports France 2 HD", "sat": "Astra 1M 19.2\u00b0e", "freq": "11856 V 29700 - 2/3", "encry": "HD Viaccess", "link": "#", "related_to": "     Villarreal   vs   Valencia"}, {"channel": "beIN Sports MENA 3 HD", "sat": "Eshail 2 25.5\u00b0e", "freq": "10810 H 27500 - 2/3", "encry": "HD Irdeto", "link": "#", "related_to": "     Villarreal   vs   Valencia"}, {"channel": "beIN Sports MENA English 2 HD", "sat": "Eshail 2 25.5\u00b0e", "freq": "11390 V 27500 - 2/3", "encry": "HD Irdeto", "link": "#", "related_to": "     Villarreal   vs   Valencia"}, {"channel": "Canal+ Sport 1 Polska HD", "sat": "Hotbird 13G 13.0\u00b0e", "freq": "11278 V 27500 - 3/4", "encry": "HD Conax", "link": "#", "related_to": "     Villarreal   vs   Valencia"}, {"channel": "DAZN 1 Italia HD", "sat": "Hotbird 13F 13.0\u00b0e", "freq": "11842 V 29900 - 5/6", "encry": "HD VideoGuard", "link": "#", "related_to": "     Villarreal   vs   Valencia"}, {"channel": "LaLiga TV Bar Espa\u00f1a HD", "sat": "Astra 1M 19.2\u00b0e", "freq": "10876 V 22000 - 5/6", "encry": "NagraVision", "link": "#", "related_to": "     Villarreal   vs   Valencia"}, {"channel": "Premier Sports 2 Ireland HD", "sat": "Astra 2F 28.2\u00b0e", "freq": "12188 H 27500 - 3/4", "encry": "HD VideoGuard", "link": "#", "related_to": "     Villarreal   vs   Valencia"}, {"channel": "Premier Sports 2 UK HD", "sat": "Astra 2G 28.2\u00b0e", "freq": "11671 H 23000 - 2/3", "encry": "HD VideoGuard", "link": "#", "related_to": "     Villarreal   vs   Valencia"}, {"channel": "Premier Sports GB Player HD", "sat": "* IPTV/Stream 0.0\u00b0", "freq": "0000 0", "encry": "", "link": "https://www.premiersports.com/fr/live-now-on-demand", "related_to": "     Villarreal   vs   Valencia"}, {"compet": "Spanish La Liga (Primera) - Week 24", "match": "     Espanyol   vs   Athletic Bilbao", "flags": {"team1": "spain", "team2": "spain"}, "time": "13:00", "date": "2025-02-16"}, {"channel": "beIN Sports MENA 3 HD", "sat": "Eshail 2 25.5\u00b0e", "freq": "10810 H 27500 - 2/3", "encry": "HD Irdeto", "link": "#", "related_to": "     Espanyol   vs   Athletic Bilbao"}, {"channel": "beIN Sports MENA French 1 HD", "sat": "Eshail 2 25.5\u00b0e", "freq": "11390 V 27500 - 2/3", "encry": "HD Irdeto", "link": "#", "related_to": "     Espanyol   vs   Athletic Bilbao"}, {"channel": "LaLiga TV Bar Espa\u00f1a HD", "sat": "Astra 1M 19.2\u00b0e", "freq": "10876 V 22000 - 5/6", "encry": "NagraVision", "link": "#", "related_to": "     Espanyol   vs   Athletic Bilbao"}, {"channel": "Premier Sports GB Player HD", "sat": "* IPTV/Stream 0.0\u00b0", "freq": "0000 0", "encry": "", "link": "https://www.premiersports.com/fr/live-now-on-demand", "related_to": "     Espanyol   vs   Athletic Bilbao"}, {"compet": "Spanish La Liga (Primera) - Week 24", "match": "     Real Valladolid   vs   Sevilla", "flags": {"team1": "spain", "team2": "spain"}, "time": "15:15", "date": "2025-02-16"}, {"channel": "beIN Sports Australia 3 HD", "sat": "* IPTV/Stream 0.0\u00b0", "freq": "0000 ", "encry": "LiveOnSat.com", "link": "#", "related_to": "     Real Valladolid   vs   Sevilla"}, {"channel": "beIN Sports France 6 HD max", "sat": "Astra 1M 19.2\u00b0e", "freq": "11856 V 29700 - 2/3", "encry": "HD NagraVision", "link": "#", "related_to": "     Real Valladolid   vs   Sevilla"}, {"channel": "beIN Sports MENA 3 HD", "sat": "Eshail 2 25.5\u00b0e", "freq": "10810 H 27500 - 2/3", "encry": "HD Irdeto", "link": "#", "related_to": "     Real Valladolid   vs   Sevilla"}, {"channel": "LaLiga TV Bar Espa\u00f1a HD", "sat": "Astra 1M 19.2\u00b0e", "freq": "10876 V 22000 - 5/6", "encry": "NagraVision", "link": "#", "related_to": "     Real Valladolid   vs   Sevilla"}, {"channel": "Premier Sports GB Player HD", "sat": "* IPTV/Stream 0.0\u00b0", "freq": "0000 0", "encry": "", "link": "https://www.premiersports.com/fr/live-now-on-demand", "related_to": "     Real Valladolid   vs   Sevilla"}, {"compet": "Spanish La Liga (Primera) - Week 24", "match": "     Mallorca   vs   Las Palmas", "flags": {"team1": "spain", "team2": "spain"}, "time": "17:30", "date": "2025-02-16"}, {"channel": "beIN Sports MENA 3 HD", "sat": "Eshail 2 25.5\u00b0e", "freq": "10810 H 27500 - 2/3", "encry": "HD Irdeto", "link": "#", "related_to": "     Mallorca   vs   Las Palmas"}, {"channel": "Canal+ Sport 1 Polska HD", "sat": "Hotbird 13G 13.0\u00b0e", "freq": "11278 V 27500 - 3/4", "encry": "HD Conax", "link": "#", "related_to": "     Mallorca   vs   Las Palmas"}, {"channel": "LaLiga TV Bar Espa\u00f1a HD", "sat": "Astra 1M 19.2\u00b0e", "freq": "10876 V 22000 - 5/6", "encry": "NagraVision", "link": "#", "related_to": "     Mallorca   vs   Las Palmas"}, {"channel": "Premier Sports 2 Ireland HD", "sat": "Astra 2F 28.2\u00b0e", "freq": "12188 H 27500 - 3/4", "encry": "HD VideoGuard", "link": "#", "related_to": "     Mallorca   vs   Las Palmas"}, {"channel": "Premier Sports 2 UK HD", "sat": "Astra 2G 28.2\u00b0e", "freq": "11671 H 23000 - 2/3", "encry": "HD VideoGuard", "link": "#", "related_to": "     Mallorca   vs   Las Palmas"}, {"channel": "Premier Sports GB Player HD", "sat": "* IPTV/Stream 0.0\u00b0", "freq": "0000 0", "encry": "", "link": "https://www.premiersports.com/fr/live-now-on-demand", "related_to": "     Mallorca   vs   Las Palmas"}, {"compet": "Spanish La Liga (Primera) - Week 24", "match": "     Real Betis   vs   Real Sociedad", "flags": {"team1": "spain", "team2": "spain"}, "time": "20:00", "date": "2025-02-16"}, {"channel": "beIN Sports Australia 3 HD", "sat": "* IPTV/Stream 0.0\u00b0", "freq": "0000 ", "encry": "LiveOnSat.com", "link": "#", "related_to": "     Real Betis   vs   Real Sociedad"}, {"channel": "beIN Sports France 1 HD", "sat": "Astra 1M 19.2\u00b0e", "freq": "11856 V 29700 - 2/3", "encry": "HD NagraVision", "link": "#", "related_to": "     Real Betis   vs   Real Sociedad"}, {"channel": "beIN Sports MENA 3 HD", "sat": "Eshail 2 25.5\u00b0e", "freq": "10810 H 27500 - 2/3", "encry": "HD Irdeto", "link": "#", "related_to": "     Real Betis   vs   Real Sociedad"}, {"channel": "beIN Sports MENA English 1 HD", "sat": "Eshail 2 25.5\u00b0e", "freq": "10850 V 27500 - 2/3", "encry": "HD Irdeto", "link": "#", "related_to": "     Real Betis   vs   Real Sociedad"}, {"channel": "LaLiga TV Bar Espa\u00f1a HD", "sat": "Astra 1M 19.2\u00b0e", "freq": "10876 V 22000 - 5/6", "encry": "NagraVision", "link": "#", "related_to": "     Real Betis   vs   Real Sociedad"}, {"channel": "Premier Sports 2 Ireland HD", "sat": "Astra 2F 28.2\u00b0e", "freq": "12188 H 27500 - 3/4", "encry": "HD VideoGuard", "link": "#", "related_to": "     Real Betis   vs   Real Sociedad"}, {"channel": "Premier Sports 2 UK HD", "sat": "Astra 2G 28.2\u00b0e", "freq": "11671 H 23000 - 2/3", "encry": "HD VideoGuard", "link": "#", "related_to": "     Real Betis   vs   Real Sociedad"}, {"channel": "Premier Sports GB Player HD", "sat": "* IPTV/Stream 0.0\u00b0", "freq": "0000 0", "encry": "", "link": "https://www.premiersports.com/fr/live-now-on-demand", "related_to": "     Real Betis   vs   Real Sociedad"}, {"compet": "Spanish La Liga (Primera) - Week 24", "match": "     Barcelona   vs   Rayo Vallecano", "flags": {"team1": "spain", "team2": "spain"}, "time": "20:00", "date": "2025-02-17"}, {"channel": "beIN Sports Australia 2 HD", "sat": "* IPTV/Stream 0.0\u00b0", "freq": "0000 ", "encry": "LiveOnSat.com", "link": "#", "related_to": "     Barcelona   vs   Rayo Vallecano"}, {"channel": "beIN Sports France 2 HD", "sat": "Astra 1M 19.2\u00b0e", "freq": "11856 V 29700 - 2/3", "encry": "HD Viaccess", "link": "#", "related_to": "     Barcelona   vs   Rayo Vallecano"}, {"channel": "ITV 4 HD", "sat": "Astra 2E 28.2\u00b0e", "freq": "10891 H 22000 - 5/6", "encry": "HD Panaccess", "link": "https://www.itv.com/watch?channel=itv4", "related_to": "     Barcelona   vs   Rayo Vallecano"}, {"channel": "ITV X (geo/R)", "sat": "* IPTV/Stream 0.0\u00b0", "freq": "0000 ", "encry": "LiveOnSat.com", "link": "https://www.itv.com/watch?channel=itv", "related_to": "     Barcelona   vs   Rayo Vallecano"}, {"channel": "LaLiga TV Bar Espa\u00f1a HD", "sat": "Astra 1M 19.2\u00b0e", "freq": "10876 V 22000 - 5/6", "encry": "NagraVision", "link": "#", "related_to": "     Barcelona   vs   Rayo Vallecano"}, {"channel": "Premier Sports 1 Ireland HD", "sat": "Astra 2F 28.2\u00b0e", "freq": "12188 H 27500 - 2/3", "encry": "HD VideoGuard", "link": "#", "related_to": "     Barcelona   vs   Rayo Vallecano"}, {"channel": "Premier Sports 1 UK HD", "sat": "Astra 2G 28.2\u00b0e", "freq": "11686 V 23000 - 2/3", "encry": "HD VideoGuard", "link": "#", "related_to": "     Barcelona   vs   Rayo Vallecano"}, {"channel": "Premier Sports GB Player HD", "sat": "* IPTV/Stream 0.0\u00b0", "freq": "0000 0", "encry": "", "link": "https://www.premiersports.com/fr/live-now-on-demand", "related_to": "     Barcelona   vs   Rayo Vallecano"}, {"compet": "Spanish La Liga (Primera) - Week 25", "match": "     Celta Vigo   vs   Osasuna", "flags": {"team1": "spain", "team2": "spain"}, "time": "20:00", "date": "2025-02-21"}, {"channel": "beIN Sports MENA 3 HD", "sat": "Eshail 2 25.5\u00b0e", "freq": "10810 H 27500 - 2/3", "encry": "HD Irdeto", "link": "#", "related_to": "     Celta Vigo   vs   Osasuna"}, {"channel": "LaLiga TV Bar Espa\u00f1a HD", "sat": "Astra 1M 19.2\u00b0e", "freq": "10876 V 22000 - 5/6", "encry": "NagraVision", "link": "#", "related_to": "     Celta Vigo   vs   Osasuna"}, {"channel": "Premier Sports 1 Ireland HD", "sat": "Astra 2F 28.2\u00b0e", "freq": "12188 H 27500 - 2/3", "encry": "HD VideoGuard", "link": "#", "related_to": "     Celta Vigo   vs   Osasuna"}, {"channel": "Premier Sports 1 UK HD", "sat": "Astra 2G 28.2\u00b0e", "freq": "11686 V 23000 - 2/3", "encry": "HD VideoGuard", "link": "#", "related_to": "     Celta Vigo   vs   Osasuna"}, {"channel": "Premier Sports GB Player HD", "sat": "* IPTV/Stream 0.0\u00b0", "freq": "0000 0", "encry": "", "link": "https://www.premiersports.com/fr/live-now-on-demand", "related_to": "     Celta Vigo   vs   Osasuna"}, {"compet": "Spanish La Liga (Primera) - Week 25", "match": "     Alav\u00e9s   vs   Espanyol", "flags": {"team1": "spain", "team2": "spain"}, "time": "13:00", "date": "2025-02-22"}, {"channel": "LaLiga TV Bar Espa\u00f1a HD", "sat": "Astra 1M 19.2\u00b0e", "freq": "10876 V 22000 - 5/6", "encry": "NagraVision", "link": "#", "related_to": "     Alav\u00e9s   vs   Espanyol"}, {"channel": "Premier Sports GB Player HD", "sat": "* IPTV/Stream 0.0\u00b0", "freq": "0000 0", "encry": "", "link": "https://www.premiersports.com/fr/live-now-on-demand", "related_to": "     Alav\u00e9s   vs   Espanyol"}, {"compet": "Spanish La Liga (Primera) - Week 25", "match": "     Rayo Vallecano   vs   Villarreal", "flags": {"team1": "spain", "team2": "spain"}, "time": "15:15", "date": "2025-02-22"}, {"channel": "LaLiga TV Bar Espa\u00f1a HD", "sat": "Astra 1M 19.2\u00b0e", "freq": "10876 V 22000 - 5/6", "encry": "NagraVision", "link": "#", "related_to": "     Rayo Vallecano   vs   Villarreal"}, {"channel": "Premier Sports GB Player HD", "sat": "* IPTV/Stream 0.0\u00b0", "freq": "0000 0", "encry": "", "link": "https://www.premiersports.com/fr/live-now-on-demand", "related_to": "     Rayo Vallecano   vs   Villarreal"}, {"compet": "Spanish La Liga (Primera) - Week 25", "match": "     Valencia   vs   Atl\u00e9tico Madrid", "flags": {"team1": "spain", "team2": "spain"}, "time": "17:30", "date": "2025-02-22"}, {"channel": "LaLiga TV Bar Espa\u00f1a HD", "sat": "Astra 1M 19.2\u00b0e", "freq": "10876 V 22000 - 5/6", "encry": "NagraVision", "link": "#", "related_to": "     Valencia   vs   Atl\u00e9tico Madrid"}, {"channel": "Premier Sports 1 Ireland HD", "sat": "Astra 2F 28.2\u00b0e", "freq": "12188 H 27500 - 2/3", "encry": "HD VideoGuard", "link": "#", "related_to": "     Valencia   vs   Atl\u00e9tico Madrid"}, {"channel": "Premier Sports 1 UK HD", "sat": "Astra 2G 28.2\u00b0e", "freq": "11686 V 23000 - 2/3", "encry": "HD VideoGuard", "link": "#", "related_to": "     Valencia   vs   Atl\u00e9tico Madrid"}, {"channel": "Premier Sports GB Player HD", "sat": "* IPTV/Stream 0.0\u00b0", "freq": "0000 0", "encry": "", "link": "https://www.premiersports.com/fr/live-now-on-demand", "related_to": "     Valencia   vs   Atl\u00e9tico Madrid"}, {"compet": "Spanish La Liga (Primera) - Week 25", "match": "     Las Palmas   vs   Barcelona", "flags": {"team1": "spain", "team2": "spain"}, "time": "20:00", "date": "2025-02-22"}, {"channel": "LaLiga TV Bar Espa\u00f1a HD", "sat": "Astra 1M 19.2\u00b0e", "freq": "10876 V 22000 - 5/6", "encry": "NagraVision", "link": "#", "related_to": "     Las Palmas   vs   Barcelona"}, {"channel": "Premier Sports 1 Ireland HD", "sat": "Astra 2F 28.2\u00b0e", "freq": "12188 H 27500 - 2/3", "encry": "HD VideoGuard", "link": "#", "related_to": "     Las Palmas   vs   Barcelona"}, {"channel": "Premier Sports 1 UK HD", "sat": "Astra 2G 28.2\u00b0e", "freq": "11686 V 23000 - 2/3", "encry": "HD VideoGuard", "link": "#", "related_to": "     Las Palmas   vs   Barcelona"}, {"channel": "Premier Sports GB Player HD", "sat": "* IPTV/Stream 0.0\u00b0", "freq": "0000 0", "encry": "", "link": "https://www.premiersports.com/fr/live-now-on-demand", "related_to": "     Las Palmas   vs   Barcelona"}, {"compet": "Spanish La Liga (Primera) - Week 25", "match": "     Athletic Bilbao   vs   Real Valladolid", "flags": {"team1": "spain", "team2": "spain"}, "time": "13:00", "date": "2025-02-23"}, {"channel": "LaLiga TV Bar Espa\u00f1a HD", "sat": "Astra 1M 19.2\u00b0e", "freq": "10876 V 22000 - 5/6", "encry": "NagraVision", "link": "#", "related_to": "     Athletic Bilbao   vs   Real Valladolid"}, {"channel": "Premier Sports 1 Ireland HD", "sat": "Astra 2F 28.2\u00b0e", "freq": "12188 H 27500 - 2/3", "encry": "HD VideoGuard", "link": "#", "related_to": "     Athletic Bilbao   vs   Real Valladolid"}, {"channel": "Premier Sports 1 UK HD", "sat": "Astra 2G 28.2\u00b0e", "freq": "11686 V 23000 - 2/3", "encry": "HD VideoGuard", "link": "#", "related_to": "     Athletic Bilbao   vs   Real Valladolid"}, {"channel": "Premier Sports GB Player HD", "sat": "* IPTV/Stream 0.0\u00b0", "freq": "0000 0", "encry": "", "link": "https://www.premiersports.com/fr/live-now-on-demand", "related_to": "     Athletic Bilbao   vs   Real Valladolid"}, {"compet": "Spanish La Liga (Primera) - Week 25", "match": "     Real Madrid   vs   Girona", "flags": {"team1": "spain", "team2": "spain"}, "time": "15:15", "date": "2025-02-23"}, {"channel": "LaLiga TV Bar Espa\u00f1a HD", "sat": "Astra 1M 19.2\u00b0e", "freq": "10876 V 22000 - 5/6", "encry": "NagraVision", "link": "#", "related_to": "     Real Madrid   vs   Girona"}, {"channel": "Premier Sports 1 Ireland HD", "sat": "Astra 2F 28.2\u00b0e", "freq": "12188 H 27500 - 2/3", "encry": "HD VideoGuard", "link": "#", "related_to": "     Real Madrid   vs   Girona"}, {"channel": "Premier Sports 1 UK HD", "sat": "Astra 2G 28.2\u00b0e", "freq": "11686 V 23000 - 2/3", "encry": "HD VideoGuard", "link": "#", "related_to": "     Real Madrid   vs   Girona"}, {"channel": "Premier Sports GB Player HD", "sat": "* IPTV/Stream 0.0\u00b0", "freq": "0000 0", "encry": "", "link": "https://www.premiersports.com/fr/live-now-on-demand", "related_to": "     Real Madrid   vs   Girona"}, {"compet": "Spanish La Liga (Primera) - Week 25", "match": "     Getafe   vs   Real Betis", "flags": {"team1": "spain", "team2": "spain"}, "time": "17:30", "date": "2025-02-23"}, {"channel": "LaLiga TV Bar Espa\u00f1a HD", "sat": "Astra 1M 19.2\u00b0e", "freq": "10876 V 22000 - 5/6", "encry": "NagraVision", "link": "#", "related_to": "     Getafe   vs   Real Betis"}, {"channel": "Premier Sports 1 Ireland HD", "sat": "Astra 2F 28.2\u00b0e", "freq": "12188 H 27500 - 2/3", "encry": "HD VideoGuard", "link": "#", "related_to": "     Getafe   vs   Real Betis"}, {"channel": "Premier Sports 1 UK HD", "sat": "Astra 2G 28.2\u00b0e", "freq": "11686 V 23000 - 2/3", "encry": "HD VideoGuard", "link": "#", "related_to": "     Getafe   vs   Real Betis"}, {"channel": "Premier Sports GB Player HD", "sat": "* IPTV/Stream 0.0\u00b0", "freq": "0000 0", "encry": "", "link": "https://www.premiersports.com/fr/live-now-on-demand", "related_to": "     Getafe   vs   Real Betis"}, {"compet": "Spanish La Liga (Primera) - Week 25", "match": "     Real Sociedad   vs   Legan\u00e9s", "flags": {"team1": "spain", "team2": "spain"}, "time": "20:00", "date": "2025-02-23"}, {"channel": "LaLiga TV Bar Espa\u00f1a HD", "sat": "Astra 1M 19.2\u00b0e", "freq": "10876 V 22000 - 5/6", "encry": "NagraVision", "link": "#", "related_to": "     Real Sociedad   vs   Legan\u00e9s"}, {"channel": "Premier Sports 1 Ireland HD", "sat": "Astra 2F 28.2\u00b0e", "freq": "12188 H 27500 - 2/3", "encry": "HD VideoGuard", "link": "#", "related_to": "     Real Sociedad   vs   Legan\u00e9s"}, {"channel": "Premier Sports 1 UK HD", "sat": "Astra 2G 28.2\u00b0e", "freq": "11686 V 23000 - 2/3", "encry": "HD VideoGuard", "link": "#", "related_to": "     Real Sociedad   vs   Legan\u00e9s"}, {"channel": "Premier Sports GB Player HD", "sat": "* IPTV/Stream 0.0\u00b0", "freq": "0000 0", "encry": "", "link": "https://www.premiersports.com/fr/live-now-on-demand", "related_to": "     Real Sociedad   vs   Legan\u00e9s"}, {"compet": "Spanish La Liga (Primera) - Week 25", "match": "     Sevilla   vs   Mallorca", "flags": {"team1": "spain", "team2": "spain"}, "time": "20:00", "date": "2025-02-24"}, {"channel": "GOL Play Espa\u00f1a HD", "sat": "*DTT 0.0\u00b0-", "freq": "0000 - -", "encry": "NagraVision", "link": "https://www.goltelevision.com/en-directo", "related_to": "     Sevilla   vs   Mallorca"}, {"channel": "IB3 Baleares", "sat": "* IPTV/Stream 0.0\u00b0", "freq": "0000 ", "encry": "", "link": "https://ib3.org/directe", "related_to": "     Sevilla   vs   Mallorca"}, {"channel": "LaLiga TV Bar Espa\u00f1a HD", "sat": "Astra 1M 19.2\u00b0e", "freq": "10876 V 22000 - 5/6", "encry": "NagraVision", "link": "#", "related_to": "     Sevilla   vs   Mallorca"}, {"channel": "Premier Sports 1 Ireland HD", "sat": "Astra 2F 28.2\u00b0e", "freq": "12188 H 27500 - 2/3", "encry": "HD VideoGuard", "link": "#", "related_to": "     Sevilla   vs   Mallorca"}, {"channel": "Premier Sports 1 UK HD", "sat": "Astra 2G 28.2\u00b0e", "freq": "11686 V 23000 - 2/3", "encry": "HD VideoGuard", "link": "#", "related_to": "     Sevilla   vs   Mallorca"}, {"channel": "Premier Sports GB Player HD", "sat": "* IPTV/Stream 0.0\u00b0", "freq": "0000 0", "encry": "", "link": "https://www.premiersports.com/fr/live-now-on-demand", "related_to": "     Sevilla   vs   Mallorca"}]}