{"footonsat": [{"compet": "Portuguese Primeira Liga - Week 1", "match": "     Sporting Lisbon   vs   Rio Ave", "flags": {"team1": "portugal", "team2": "portugal"}, "time": "19:15", "date": "2024-08-09"}, {"channel": "Sport TV1 Portugal HD", "sat": "Hispasat 30W-5 30.0\u00b0w", "freq": "12246 H 27500 - 3/4", "encry": "HD NagraVision", "link": "#", "related_to": "     Sporting Lisbon   vs   Rio Ave"}, {"channel": "Thriller TV+ [online] ($/geo/R)", "sat": "* IPTV/Stream 0.0\u00b0", "freq": "0000 0", "encry": "", "link": "https://www.trillertv.com/join/trillertv-subscription/", "related_to": "     Sporting Lisbon   vs   Rio Ave"}, {"compet": "Portuguese Primeira Liga - Week 1", "match": "     FC Porto   vs   Gil Vicente", "flags": {"team1": "portugal", "team2": "portugal"}, "time": "19:30", "date": "2024-08-10"}, {"channel": "beIN Sports France 5 HD max", "sat": "Astra 1M 19.2\u00b0e", "freq": "11856 V 29700 - 2/3", "encry": "HD NagraVision", "link": "#", "related_to": "     FC Porto   vs   Gil Vicente"}, {"channel": "Thriller TV+ [online] ($/geo/R)", "sat": "* IPTV/Stream 0.0\u00b0", "freq": "0000 0", "encry": "", "link": "https://www.trillertv.com/join/trillertv-subscription/", "related_to": "     FC Porto   vs   Gil Vicente"}, {"compet": "Portuguese Primeira Liga - Week 1", "match": "     Famalic\u00e3o   vs   Benfica", "flags": {"team1": "portugal", "team2": "portugal"}, "time": "17:00", "date": "2024-08-11"}, {"channel": "Thriller TV+ [online] ($/geo/R)", "sat": "* IPTV/Stream 0.0\u00b0", "freq": "0000 0", "encry": "", "link": "https://www.trillertv.com/join/trillertv-subscription/", "related_to": "     Famalic\u00e3o   vs   Benfica"}]}