{"footonsat": [{"compet": "UEFA U-17 Championship 2025 Qualifiers - Group 5, Round 1", "match": "     Portugal U-17   vs   Liechtenstein U-17", "flags": {"team1": "portugal", "team2": "liechtenstein"}, "time": "11:00", "date": "2024-11-13"}, {"channel": "Canal 11 Portugal HD", "sat": "Hispasat 30W-5 30.0\u00b0w", "freq": "12437 H 27500 - 3/4", "encry": "HD NagraVision", "link": "#", "related_to": "     Portugal U-17   vs   Liechtenstein U-17"}, {"compet": "UEFA U-19 Championship Qualifiers - Group Stage", "match": "     Armenia U-19   vs   Croatia U-19", "flags": {"team1": "armenia", "team2": "croatia"}, "time": "12:00", "date": "2024-11-13"}, {"channel": "MAX Sport 1 Hrvatska HD", "sat": "Eutelsat 16A 16.0\u00b0e", "freq": "11512 H 30000 - 3/4", "encry": "HD NagraVision", "link": "#", "related_to": "     Armenia U-19   vs   Croatia U-19"}, {"compet": "Uruguay Primera Divisi\u00f3n - Clausura - 12", "match": "     River Plate   vs   Miramar", "flags": {"team1": "uraguay", "team2": "uraguay"}, "time": "12:45", "date": "2024-11-13"}, {"channel": "GolTV Play ($/geo/R)", "sat": "* IPTV/Stream 0.0\u00b0", "freq": "0000 0", "encry": "", "link": "https://play.goltv.tv/", "related_to": "     River Plate   vs   Miramar"}, {"channel": "viju+ Sport HD", "sat": "KazSat 3 58.5\u00b0e", "freq": "10720 H 30000 - 3/4", "encry": "Irdeto", "link": "#", "related_to": "     River Plate   vs   Miramar"}, {"compet": "CAF African Cup of Nations Qualifiers - Group J, Round 5", "match": "     Namibia   vs   Cameroon", "flags": {"team1": "namibia", "team2": "cameroon"}, "time": "13:00", "date": "2024-11-13"}, {"channel": "beIN Sports 1 HD (Astro)", "sat": "Measat 3b 91.5\u00b0e", "freq": "11142 V 30000 - 5/6", "encry": "HD VideoGuard", "link": "#", "related_to": "     Namibia   vs   Cameroon"}, {"channel": "beIN Sports France 2 HD", "sat": "Astra 1M 19.2\u00b0e", "freq": "11856 V 29700 - 2/3", "encry": "HD Viaccess", "link": "#", "related_to": "     Namibia   vs   Cameroon"}, {"channel": "beIN Sports MENA French 2 HD", "sat": "Eshail 2 25.5\u00b0e", "freq": "10850 H 27500 - 2/3", "encry": "HD Irdeto", "link": "#", "related_to": "     Namibia   vs   Cameroon"}, {"channel": "Sportdigital FUSSBALL HD", "sat": "Astra 1L 19.2\u00b0e", "freq": "11186 V 22000 - 2/3", "encry": "HD VideoGuard", "link": "#", "related_to": "     Namibia   vs   Cameroon"}, {"compet": "Slovak Cup - Round of 16", "match": "     Ruzomberok   vs   Kom\u00e1rno", "flags": {"team1": "slovakia", "team2": "slovakia"}, "time": "15:00", "date": "2024-11-13"}, {"channel": "Futbalnet TV [online]", "sat": "* IPTV/Stream 0.0\u00b0", "freq": "0000 0", "encry": "", "link": "https://futbalnet.tv/", "related_to": "     Ruzomberok   vs   Kom\u00e1rno"}, {"compet": "UEFA Womens Champions League - Group Stage: Round 3", "match": "     Galatasaray   vs   Wolfsburg", "flags": {"team1": "turkey", "team2": "germany"}, "time": "17:45", "date": "2024-11-13"}, {"channel": "beIN Sports MENA English 2 HD", "sat": "Eshail 2 25.5\u00b0e", "freq": "11390 V 27500 - 2/3", "encry": "HD Irdeto", "link": "#", "related_to": "     Galatasaray   vs   Wolfsburg"}, {"channel": "DAZN 1 Bar Deutsch HD", "sat": "Astra 1N 19.2\u00b0e", "freq": "12070 H 27500 - 9/10", "encry": "HD VideoGuard", "link": "#", "related_to": "     Galatasaray   vs   Wolfsburg"}, {"channel": "DAZN 2 Portugal HD", "sat": "Hispasat 30W-5 30.0\u00b0w", "freq": "12246 H 27500 - 3/4", "encry": "HD NagraVision", "link": "#", "related_to": "     Galatasaray   vs   Wolfsburg"}, {"channel": "DAZN Deutsch ($/geo/R)", "sat": "* IPTV/Stream 0.0\u00b0", "freq": "0000 ", "encry": "LiveOnSat.com", "link": "#", "related_to": "     Galatasaray   vs   Wolfsburg"}, {"channel": "DAZN Espa\u00f1a ($/geo/R)", "sat": "* IPTV/Stream 0.0\u00b0", "freq": "0000 ", "encry": "", "link": "#", "related_to": "     Galatasaray   vs   Wolfsburg"}, {"channel": "DAZN France ($/geo/R)", "sat": "* IPTV/Stream 0.0\u00b0", "freq": "0000 ", "encry": "", "link": "#", "related_to": "     Galatasaray   vs   Wolfsburg"}, {"channel": "DAZN Worldwide ($/geo/R)", "sat": "* IPTV/Stream 0.0\u00b0", "freq": "0000 ", "encry": "", "link": "https://www.dazn.com", "related_to": "     Galatasaray   vs   Wolfsburg"}, {"channel": "YouTube: DAZN Women", "sat": "* IPTV/Stream 0.0\u00b0", "freq": "0000 0", "encry": "", "link": "https://www.youtube.com/@DAZNWomensFootball", "related_to": "     Galatasaray   vs   Wolfsburg"}, {"compet": "UEFA Womens Champions League - Group Stage: Round 3", "match": "     Real Madrid   vs   Twente", "flags": {"team1": "spain", "team2": "holland"}, "time": "17:45", "date": "2024-11-13"}, {"channel": "beIN Sports MENA English 1 HD", "sat": "Eshail 2 25.5\u00b0e", "freq": "10850 V 27500 - 2/3", "encry": "HD Irdeto", "link": "#", "related_to": "     Real Madrid   vs   Twente"}, {"channel": "beIN Sports MENA Global HD", "sat": "Eshail 2 25.5\u00b0e", "freq": "10810 V 27500 - 2/3", "encry": "FTA", "link": "#", "related_to": "     Real Madrid   vs   Twente"}, {"channel": "DAZN 1 Portugal HD", "sat": "Hispasat 30W-5 30.0\u00b0w", "freq": "12399 H 27500 - 3/4", "encry": "HD NagraVision", "link": "#", "related_to": "     Real Madrid   vs   Twente"}, {"channel": "DAZN Deutsch ($/geo/R)", "sat": "* IPTV/Stream 0.0\u00b0", "freq": "0000 ", "encry": "LiveOnSat.com", "link": "#", "related_to": "     Real Madrid   vs   Twente"}, {"channel": "DAZN Espa\u00f1a ($/geo/R)", "sat": "* IPTV/Stream 0.0\u00b0", "freq": "0000 ", "encry": "", "link": "#", "related_to": "     Real Madrid   vs   Twente"}, {"channel": "DAZN France ($/geo/R)", "sat": "* IPTV/Stream 0.0\u00b0", "freq": "0000 ", "encry": "", "link": "#", "related_to": "     Real Madrid   vs   Twente"}, {"channel": "DAZN Worldwide ($/geo/R)", "sat": "* IPTV/Stream 0.0\u00b0", "freq": "0000 ", "encry": "", "link": "https://www.dazn.com", "related_to": "     Real Madrid   vs   Twente"}, {"channel": "YouTube: DAZN Women", "sat": "* IPTV/Stream 0.0\u00b0", "freq": "0000 0", "encry": "", "link": "https://www.youtube.com/@DAZNWomensFootball", "related_to": "     Real Madrid   vs   Twente"}, {"compet": "Uruguay Primera Divisi\u00f3n - Clausura - 12", "match": "     F\u00e9nix   vs   Nacional Montevideo", "flags": {"team1": "uraguay", "team2": "uraguay"}, "time": "19:30", "date": "2024-11-13"}, {"channel": "GolTV Play ($/geo/R)", "sat": "* IPTV/Stream 0.0\u00b0", "freq": "0000 0", "encry": "", "link": "https://play.goltv.tv/", "related_to": "     F\u00e9nix   vs   Nacional Montevideo"}, {"compet": "UEFA Womens Champions League - Group Stage: Round 3", "match": "     Celtic   vs   Chelsea", "flags": {"team1": "scotland", "team2": "england"}, "time": "20:00", "date": "2024-11-13"}, {"channel": "beIN Sports MENA English 1 HD", "sat": "Eshail 2 25.5\u00b0e", "freq": "10850 V 27500 - 2/3", "encry": "HD Irdeto", "link": "#", "related_to": "     Celtic   vs   Chelsea"}, {"channel": "beIN Sports MENA Global HD", "sat": "Eshail 2 25.5\u00b0e", "freq": "10810 V 27500 - 2/3", "encry": "FTA", "link": "#", "related_to": "     Celtic   vs   Chelsea"}, {"channel": "DAZN 2 Portugal HD", "sat": "Hispasat 30W-5 30.0\u00b0w", "freq": "12246 H 27500 - 3/4", "encry": "HD NagraVision", "link": "#", "related_to": "     Celtic   vs   Chelsea"}, {"channel": "DAZN Deutsch ($/geo/R)", "sat": "* IPTV/Stream 0.0\u00b0", "freq": "0000 ", "encry": "LiveOnSat.com", "link": "#", "related_to": "     Celtic   vs   Chelsea"}, {"channel": "DAZN Espa\u00f1a ($/geo/R)", "sat": "* IPTV/Stream 0.0\u00b0", "freq": "0000 ", "encry": "", "link": "#", "related_to": "     Celtic   vs   Chelsea"}, {"channel": "DAZN France ($/geo/R)", "sat": "* IPTV/Stream 0.0\u00b0", "freq": "0000 ", "encry": "", "link": "#", "related_to": "     Celtic   vs   Chelsea"}, {"channel": "DAZN Worldwide ($/geo/R)", "sat": "* IPTV/Stream 0.0\u00b0", "freq": "0000 ", "encry": "", "link": "https://www.dazn.com", "related_to": "     Celtic   vs   Chelsea"}, {"channel": "TNT Sports 1 UK HD", "sat": "NSS 12 57.0\u00b0e", "freq": "3798 R 19167 - 3/5", "encry": "Irdeto [c]", "link": "#", "related_to": "     Celtic   vs   Chelsea"}, {"channel": "YouTube: DAZN Women", "sat": "* IPTV/Stream 0.0\u00b0", "freq": "0000 0", "encry": "", "link": "https://www.youtube.com/@DAZNWomensFootball", "related_to": "     Celtic   vs   Chelsea"}, {"compet": "UEFA Womens Champions League - Group Stage: Round 3", "match": "     Roma   vs   Lyon", "flags": {"team1": "italy", "team2": "france"}, "time": "20:00", "date": "2024-11-13"}, {"channel": "beIN Sports MENA English 2 HD", "sat": "Eshail 2 25.5\u00b0e", "freq": "11390 V 27500 - 2/3", "encry": "HD Irdeto", "link": "#", "related_to": "     Roma   vs   Lyon"}, {"channel": "DAZN 1 Bar Deutsch HD", "sat": "Astra 1N 19.2\u00b0e", "freq": "12070 H 27500 - 9/10", "encry": "HD VideoGuard", "link": "#", "related_to": "     Roma   vs   Lyon"}, {"channel": "DAZN 1 Portugal HD", "sat": "Hispasat 30W-5 30.0\u00b0w", "freq": "12399 H 27500 - 3/4", "encry": "HD NagraVision", "link": "#", "related_to": "     Roma   vs   Lyon"}, {"channel": "DAZN Deutsch ($/geo/R)", "sat": "* IPTV/Stream 0.0\u00b0", "freq": "0000 ", "encry": "LiveOnSat.com", "link": "#", "related_to": "     Roma   vs   Lyon"}, {"channel": "DAZN Espa\u00f1a ($/geo/R)", "sat": "* IPTV/Stream 0.0\u00b0", "freq": "0000 ", "encry": "", "link": "#", "related_to": "     Roma   vs   Lyon"}, {"channel": "DAZN France ($/geo/R)", "sat": "* IPTV/Stream 0.0\u00b0", "freq": "0000 ", "encry": "", "link": "#", "related_to": "     Roma   vs   Lyon"}, {"channel": "DAZN Worldwide ($/geo/R)", "sat": "* IPTV/Stream 0.0\u00b0", "freq": "0000 ", "encry": "", "link": "https://www.dazn.com", "related_to": "     Roma   vs   Lyon"}, {"channel": "VG+ Sport Norge ($/geo/R)", "sat": "* IPTV/Stream 0.0\u00b0", "freq": "0000 ", "encry": "", "link": "https://www.vgtv.no/live", "related_to": "     Roma   vs   Lyon"}, {"channel": "YouTube: DAZN Women", "sat": "* IPTV/Stream 0.0\u00b0", "freq": "0000 0", "encry": "", "link": "https://www.youtube.com/@DAZNWomensFootball", "related_to": "     Roma   vs   Lyon"}, {"compet": "Uruguay Primera Divisi\u00f3n - Clausura - 12", "match": "     Cerro Largo   vs   Liverpool", "flags": {"team1": "uraguay", "team2": "uraguay"}, "time": "22:00", "date": "2024-11-13"}, {"channel": "GolTV Play ($/geo/R)", "sat": "* IPTV/Stream 0.0\u00b0", "freq": "0000 0", "encry": "", "link": "https://play.goltv.tv/", "related_to": "     Cerro Largo   vs   Liverpool"}, {"channel": "viju+ Sport HD", "sat": "KazSat 3 58.5\u00b0e", "freq": "10720 H 30000 - 3/4", "encry": "Irdeto", "link": "#", "related_to": "     Cerro Largo   vs   Liverpool"}, {"compet": "Brazilian S\u00e9rie A - Week 33", "match": "     Flamengo   vs   Atl\u00e9tico Mineiro", "flags": {"team1": "brazil", "team2": "brazil"}, "time": "23:00", "date": "2024-11-13"}, {"channel": "Canal 11 Portugal HD", "sat": "Hispasat 30W-5 30.0\u00b0w", "freq": "12437 H 27500 - 3/4", "encry": "HD NagraVision", "link": "#", "related_to": "     Flamengo   vs   Atl\u00e9tico Mineiro"}, {"channel": "MATCH! Futbol 3 HD", "sat": "Horizons 2 84.8\u00b0e", "freq": "11840 H 28800 - 2/3", "encry": "MPEG-4 Conax", "link": "#", "related_to": "     Flamengo   vs   Atl\u00e9tico Mineiro"}, {"channel": "Sport 1 Baltic", "sat": "* IPTV/Stream 0.0\u00b0", "freq": "0000 0", "encry": "", "link": "#", "related_to": "     Flamengo   vs   Atl\u00e9tico Mineiro"}, {"channel": "Sport 1 Ukraine", "sat": "* IPTV/Stream 0.0\u00b0", "freq": "0000 0", "encry": "", "link": "#", "related_to": "     Flamengo   vs   Atl\u00e9tico Mineiro"}, {"channel": "Sport 3 Ukraine", "sat": "* IPTV/Stream 0.0\u00b0", "freq": "0000 0", "encry": "", "link": "#", "related_to": "     Flamengo   vs   Atl\u00e9tico Mineiro"}, {"last_update": "03:42  13-11-2024"}]}